KernelTreelets/KernelTreelets.py
KernelTreelets/__init__.py
KernelTreelets-0.5.1.dist-info/LICENSE
KernelTreelets-0.5.1.dist-info/METADATA
KernelTreelets-0.5.1.dist-info/WHEEL
KernelTreelets-0.5.1.dist-info/top_level.txt
KernelTreelets-0.5.1.dist-info/RECORD
