Metadata-Version: 2.1
Name: KernelTreelets
Version: 0.5.1
Summary: # Kernel Treelets (KT)
